MANIFEST.in
setup.py
../../version.ini
grr_response_server/__init__.py
grr_response_server/access_control.py
grr_response_server/action_registry.py
grr_response_server/artifact.py
grr_response_server/artifact_registry.py
grr_response_server/artifact_registry_test.py
grr_response_server/artifact_test.py
grr_response_server/artifact_utils_test.py
grr_response_server/base_stats_server.py
grr_response_server/base_stats_server_test.py
grr_response_server/blob_store.py
grr_response_server/blob_store_test_mixin.py
grr_response_server/client_fixture.py
grr_response_server/client_index.py
grr_response_server/client_index_test.py
grr_response_server/command_signer.py
grr_response_server/command_signer_test_mixin.py
grr_response_server/communicator.py
grr_response_server/config_validation_test.py
grr_response_server/cronjobs.py
grr_response_server/cronjobs_test.py
grr_response_server/data_store.py
grr_response_server/data_store_utils.py
grr_response_server/data_store_utils_test.py
grr_response_server/distro_entry.py
grr_response_server/email_alerts.py
grr_response_server/email_alerts_test.py
grr_response_server/ephemeral_key_command_signer.py
grr_response_server/ephemeral_key_command_signer_test.py
grr_response_server/events.py
grr_response_server/events_test.py
grr_response_server/export.py
grr_response_server/export_converters_registry.py
grr_response_server/export_test.py
grr_response_server/file_store.py
grr_response_server/file_store_test.py
grr_response_server/fleetspeak.py
grr_response_server/fleetspeak_connector.py
grr_response_server/fleetspeak_cps.py
grr_response_server/fleetspeak_cps_test.py
grr_response_server/fleetspeak_utils.py
grr_response_server/fleetspeak_utils_test.py
grr_response_server/flow.py
grr_response_server/flow_base.py
grr_response_server/flow_base_test.py
grr_response_server/flow_responses.py
grr_response_server/flow_responses_test.py
grr_response_server/flow_test.py
grr_response_server/foreman.py
grr_response_server/foreman_rules.py
grr_response_server.egg-info/PKG-INFO
grr_response_server.egg-info/SOURCES.txt
grr_response_server.egg-info/dependency_links.txt
grr_response_server.egg-info/entry_points.txt
grr_response_server.egg-info/requires.txt
grr_response_server.egg-info/top_level.txt
