Metadata-Version: 2.4
Name: grr-response-server
Version: 4.0.0.post0
Summary: The GRR Rapid Response Server.
Home-page: https://github.com/google/grr
Maintainer: GRR Development Team
Maintainer-email: grr-dev@googlegroups.com
License: Apache License, Version 2.0
Requires-Dist: google-api-python-client==1.12.11
Requires-Dist: google-auth==2.23.3
Requires-Dist: google-cloud-storage==2.13.0
Requires-Dist: google-cloud-pubsub==2.18.4
Requires-Dist: grr-api-client==4.0.0post0
Requires-Dist: grr-response-client-builder==4.0.0post0
Requires-Dist: grr-response-core==4.0.0post0
Requires-Dist: ipython==7.15.0
Requires-Dist: Jinja2==3.1.2
Requires-Dist: pexpect==4.8.0
Requires-Dist: portpicker==1.6.0b1
Requires-Dist: prometheus_client==0.16.0
Requires-Dist: pyjwt==2.6.0
Requires-Dist: pyOpenSSL==21.0.0
Requires-Dist: python-crontab==2.5.1
Requires-Dist: python-debian==0.1.49
Requires-Dist: Werkzeug==2.1.2
Provides-Extra: mysqldatastore
Requires-Dist: mysqlclient<=1.4.6,>=1.3.10; extra == "mysqldatastore"
Requires-Dist: fleetspeak-server-bin==0.1.13; sys_platform == "linux"
Dynamic: home-page
Dynamic: license
Dynamic: maintainer
Dynamic: maintainer-email
Dynamic: provides-extra
Dynamic: requires-dist
Dynamic: summary
